fewsats/__init__.py
fewsats/_modidx.py
fewsats/core.py
fewsats/l402.py
fewsats/main.py
fewsats_python-0.0.15.dist-info/METADATA
fewsats_python-0.0.15.dist-info/WHEEL
fewsats_python-0.0.15.dist-info/entry_points.txt
fewsats_python-0.0.15.dist-info/licenses/LICENSE
fewsats_python-0.0.15.dist-info/RECORD
