Metadata-Version: 2.4
Name: fewsats-python
Version: 0.0.15
Summary: CLI for Fewsats operations using MCP server tooling
Author-email: Jordi Montes <jordi@fewsats.com>, Pol Alvarez <pol@fewsats.com>
License: MIT
License-File: LICENSE
Keywords: cli,fewsats,sdk
Requires-Python: >=3.10
Requires-Dist: fewsats
Requires-Dist: mcp[cli]
